HISTORY.txt
LICENSE.txt
MANIFEST.in
README.md
setup.cfg
setup.py
sparc/__init__.py
sparc.db.egg-info/PKG-INFO
sparc.db.egg-info/SOURCES.txt
sparc.db.egg-info/dependency_links.txt
sparc.db.egg-info/entry_points.txt
sparc.db.egg-info/namespace_packages.txt
sparc.db.egg-info/not-zip-safe
sparc.db.egg-info/requires.txt
sparc.db.egg-info/top_level.txt
sparc/db/__init__.py
sparc/db/configure.zcml
sparc/db/interfaces.py
sparc/db/memory.zcml
sparc/db/sql.py
sparc/db/report/__init__.py
sparc/db/report/configure.zcml
sparc/db/report/interfaces.py
sparc/db/report/period.py
sparc/db/report/tests/__init__.py
sparc/db/report/tests/test_period.py
sparc/db/tests/__init__.py
sparc/db/tests/test_saconfig.py
sparc/db/tests/test_sql.py